aerosols/__init__.py
aerosols/cli.py
aerosols/fractals.py
aerosols/mie.py
aerosols/tholins.py
aerosols/version.py
aerosols/data/optical_index.db
titan_aerosols-0.4.0.dist-info/LICENSE.md
titan_aerosols-0.4.0.dist-info/METADATA
titan_aerosols-0.4.0.dist-info/WHEEL
titan_aerosols-0.4.0.dist-info/entry_points.txt
titan_aerosols-0.4.0.dist-info/top_level.txt
titan_aerosols-0.4.0.dist-info/RECORD
