Metadata-Version: 2.1
Name: titan-aerosols
Version: 0.4.0
Summary: Titan aerosols models
Home-page: http://github.com/seignovert/python-titan-aerosols
Author: Benoit Seignovert, Pascal Rannou, Loic Rossi
Author-email: python@seignovert.fr
License: MIT
Keywords: Titan,Aerosols,Scattering models,Mie,Fractal
Platform: UNKNOWN
Classifier: Development Status :: 4 - Beta
Classifier: Intended Audience :: Science/Research
Classifier: License :: OSI Approved :: MIT License
Classifier: Natural Language :: English
Classifier: Programming Language :: Python
Classifier: Programming Language :: Python :: 3.7
Classifier: Programming Language :: Python :: 3.8
Classifier: Programming Language :: Python :: 3.9
Classifier: Programming Language :: Python :: 3.10
Classifier: Topic :: Scientific/Engineering
Classifier: Topic :: Scientific/Engineering :: Astronomy
Classifier: Topic :: Scientific/Engineering :: Atmospheric Science
Requires-Python: >=3.8
Requires-Dist: numpy (>=1.20)
